EQL/__init__.py
EQL/layer.py
EQL/model.py
EQL_NN-2.1.0.dist-info/LICENSE
EQL_NN-2.1.0.dist-info/METADATA
EQL_NN-2.1.0.dist-info/WHEEL
EQL_NN-2.1.0.dist-info/top_level.txt
EQL_NN-2.1.0.dist-info/RECORD
