Metadata-Version: 2.1
Name: EQL-NN
Version: 2.1.0
Summary: A Tensorflow implementation of the Equation Learning Based Neural Network Model
Home-page: https://github.com/KristofPusztai/EQL
Author: Kristof Pusztai
Author-email: kpusztai@berkeley.edu
Classifier: Programming Language :: Python :: 3
Classifier: License :: OSI Approved :: MIT License
Classifier: Operating System :: OS Independent
Requires-Python: >=3.8
License-File: LICENSE
Requires-Dist: tensorflow >=2.11
Requires-Dist: numpy
Requires-Dist: sympy
